kleinkram/__init__.py
kleinkram/__main__.py
kleinkram/_version.py
kleinkram/auth.py
kleinkram/config.py
kleinkram/core.py
kleinkram/errors.py
kleinkram/main.py
kleinkram/models.py
kleinkram/printing.py
kleinkram/py.typed
kleinkram/types.py
kleinkram/utils.py
kleinkram/wrappers.py
kleinkram/api/__init__.py
kleinkram/api/client.py
kleinkram/api/deser.py
kleinkram/api/file_transfer.py
kleinkram/api/pagination.py
kleinkram/api/query.py
kleinkram/api/routes.py
kleinkram/cli/__init__.py
kleinkram/cli/_action.py
kleinkram/cli/_download.py
kleinkram/cli/_endpoint.py
kleinkram/cli/_file.py
kleinkram/cli/_file_validator.py
kleinkram/cli/_list.py
kleinkram/cli/_mission.py
kleinkram/cli/_project.py
kleinkram/cli/_run.py
kleinkram/cli/_upload.py
kleinkram/cli/_verify.py
kleinkram/cli/app.py
kleinkram/cli/error_handling.py
tests/__init__.py
tests/backend_fixtures.py
tests/conftest.py
tests/generate_test_data.py
tests/test_config.py
tests/test_core.py
tests/test_end_to_end.py
tests/test_error_handling.py
tests/test_fixtures.py
tests/test_printing.py
tests/test_query.py
tests/test_utils.py
tests/test_wrappers.py
kleinkram-0.57.0.dist-info/METADATA
kleinkram-0.57.0.dist-info/WHEEL
kleinkram-0.57.0.dist-info/entry_points.txt
kleinkram-0.57.0.dist-info/top_level.txt
kleinkram-0.57.0.dist-info/RECORD
