Metadata-Version: 2.4
Name: kleinkram
Version: 0.57.0
Summary: give me your bags
Author: Cyrill Püntener, Dominique Garmier, Johann Schwabe
Author-email: pucyril@ethz.ch, dgarmier@ethz.ch, jschwab@ethz.ch
Classifier: Programming Language :: Python :: 3
Classifier: Programming Language :: Python :: 3 :: Only
Classifier: Programming Language :: Python :: 3.8
Classifier: Programming Language :: Python :: 3.9
Classifier: Programming Language :: Python :: 3.10
Classifier: Programming Language :: Python :: 3.11
Classifier: Programming Language :: Python :: 3.12
Classifier: Programming Language :: Python :: Implementation :: CPython
Requires-Python: >=3.8
Requires-Dist: boto3
Requires-Dist: botocore
Requires-Dist: click
Requires-Dist: httpx
Requires-Dist: python-dateutil
Requires-Dist: pyyaml
Requires-Dist: requests
Requires-Dist: rich
Requires-Dist: tqdm
Requires-Dist: typer
